[{"n": 22, "k": 2, "d": 3, "G_X": [[1, 1, 0, 0, 0, 0, 0, 0, 1, 1, 1, 1, 0, 0, 0, 0, 0, 0, 0, 0, 0, 0], [0, 1, 1, 1, 1, 1, 1, 1, 1, 1, 1, 0, 1, 1, 0, 0, 0, 0, 0, 0, 0, 0], [0, 1, 1, 1, 0, 0, 1, 0, 0, 0, 1, 1, 0, 0, 1, 1, 0, 0, 0, 0, 0, 0], [0, 0, 0, 1, 1, 1, 1, 1, 1, 1, 1, 0, 0, 0, 1, 1, 0, 0, 0, 0, 0, 0], [0, 0, 0, 0, 0, 1, 1, 1, 0, 1, 1, 0, 0, 0, 1, 0, 1, 0, 0, 0, 0, 0], [0, 0, 0, 0, 0, 0, 1, 1, 1, 1, 0, 1, 0, 0, 1, 0, 1, 1, 1, 0, 0, 0], [0, 0, 0, 0, 0, 0, 0, 1, 0, 0, 1, 1, 1, 0, 1, 1, 0, 1, 1, 0, 1, 0], [0, 0, 0, 0, 0, 0, 0, 0, 1, 0, 0, 0, 0, 1, 1, 1, 1, 0, 1, 0, 0, 0], [0, 0, 0, 0, 0, 0, 0, 0, 0, 0, 0, 1, 1, 0, 0, 1, 0, 0, 1, 1, 1, 1], [0, 0, 0, 0, 0, 0, 0, 0, 0, 0, 0, 0, 0, 0, 0, 0, 1, 1, 1, 0, 1, 1]], "G_Z": [[1, 1, 1, 1, 1, 1, 0, 1, 0, 1, 1, 0, 0, 0, 0, 0, 0, 0, 0, 0, 0, 0], [0, 1, 0, 1, 1, 1, 1, 0, 0, 0, 0, 1, 1, 0, 0, 0, 0, 0, 0, 0, 0, 0], [0, 0, 1, 1, 1, 1, 0, 1, 0, 1, 0, 1, 1, 1, 1, 0, 0, 0, 0, 0, 0, 0], [0, 0, 0, 0, 1, 1, 0, 0, 0, 1, 0, 1, 0, 1, 0, 1, 0, 0, 0, 0, 0, 0], [0, 0, 0, 0, 0, 0, 0, 1, 1, 0, 1, 0, 1, 0, 0, 1, 0, 0, 0, 0, 0, 0], [0, 0, 0, 0, 0, 1, 1, 0, 1, 0, 1, 0, 0, 0, 0, 0, 1, 1, 0, 0, 0, 0], [0, 0, 0, 0, 0, 0, 0, 0, 1, 1, 0, 0, 0, 0, 1, 1, 0, 0, 1, 1, 1, 0], [0, 0, 0, 0, 0, 0, 0, 1, 1, 1, 1, 1, 1, 1, 1, 1, 0, 1, 0, 0, 1, 0], [0, 0, 0, 0, 0, 0, 0, 0, 0, 0, 0, 0, 1, 1, 1, 1, 1, 0, 0, 1, 1, 0], [0, 0, 0, 0, 0, 0, 0, 0, 0, 0, 0, 0, 0, 0, 1, 1, 1, 1, 1, 1, 0, 1]], "gates": [".h(2)", ".h(4)", ".h(6)", ".h(8)", ".h(10)", ".h(12)", ".h(14)", ".h(16)", ".h(18)", ".h(20)", ".cx(2,3)", ".cx(4,5)", ".cx(6,7)", ".cx(8,9)", ".cx(10,11)", ".cx(12,13)", ".cx(14,15)", ".cx(16,17)", ".cx(18,19)", ".cx(20,21)", ".cx(2, 1)", ".cx(4, 3)", ".cx(6, 5)", ".cx(8, 7)", ".cx(10, 9)", ".cx(12, 11)", ".cx(14, 13)", ".cx(16, 15)", ".cx(18, 17)", ".cx(20, 19)", ".cx(1, 2)", ".cx(0, 1)", ".cx(3, 4)", ".cx(2, 3)", ".cx(3, 2)", ".cx(1, 2)", ".cx(1, 0)", ".cx(5, 4)", ".cx(5, 6)", ".cx(7, 6)", ".cx(7, 8)", ".cx(9, 8)", ".cx(9, 10)", ".cx(11, 10)", ".cx(11, 12)", ".cx(4, 3)", ".cx(13, 12)", ".cx(13, 14)", ".cx(15, 14)", ".cx(15, 16)", ".cx(17, 16)", ".cx(17, 18)", ".cx(19, 18)", ".cx(19, 20)", ".cx(4, 5)", ".cx(3, 2)", ".cx(2, 3)", ".cx(2, 1)", ".cx(3, 4)", ".cx(6, 5)", ".cx(6, 7)", ".cx(8, 7)", ".cx(8, 9)", ".cx(9, 10)", ".cx(10, 9)", ".cx(9, 8)", ".cx(10, 11)", ".cx(5, 6)", ".cx(7, 6)", ".cx(5, 4)", ".cx(7, 8)", ".cx(12, 11)", ".cx(12, 13)", ".cx(14, 15)", ".cx(13, 14)", ".cx(14, 13)", ".cx(13, 12)", ".cx(9, 10)", ".cx(11, 10)", ".cx(11, 12)", ".cx(12, 13)", ".cx(12, 11)", ".cx(10, 9)", ".cx(8, 9)", ".cx(8, 7)", ".cx(7, 8)", ".cx(6, 7)", ".cx(7, 8)", ".cx(4, 5)", ".cx(4, 3)", ".cx(2, 3)", ".cx(14, 13)", ".cx(16, 17)", ".cx(15, 16)", ".cx(16, 15)", ".cx(14, 15)", ".cx(18, 19)", ".cx(17, 18)", ".cx(18, 19)", ".cx(18, 17)", ".cx(9, 10)", ".cx(10, 11)", ".cx(9, 10)", ".cx(6, 5)", ".cx(15, 14)", ".cx(16, 17)", ".cx(20, 21)", ".cx(19, 20)", ".cx(14, 13)", ".cx(13, 14)", ".cx(13, 12)", ".cx(11, 12)", ".cx(11, 10)", ".cx(5, 6)", ".cx(7, 6)", ".cx(8, 9)", ".cx(9, 8)", ".cx(9, 10)", ".cx(15, 16)", ".cx(14, 13)", ".cx(12, 13)", ".cx(12, 11)", ".cx(10, 11)", ".cx(17, 16)", ".cx(14, 15)", ".cx(10, 9)", ".cx(9, 10)", ".cx(17, 18)", ".cx(19, 18)", ".cx(20, 19)", ".cx(8, 9)", ".cx(8, 7)", ".cx(7, 8)", ".cx(8, 7)", ".cx(19, 18)", ".cx(19, 20)", ".cx(9, 8)", ".cx(8, 9)", ".cx(9, 8)", ".cx(9, 8)", ".cx(9, 8)", ".cx(9, 8)", ".cx(9, 8)", ".cx(9, 8)", ".cx(9, 8)", ".cx(9, 8)", ".cx(9, 8)", ".cx(9, 8)", ".cx(9, 8)", ".cx(9, 8)"]}, {"n": 22, "k": 2, "d": 4, "G_X": [[1, 1, 1, 0, 0, 0, 1, 1, 1, 1, 1, 1, 0, 0, 0, 0, 0, 0, 0, 0, 0, 0], [0, 1, 0, 1, 0, 0, 0, 1, 1, 1, 1, 1, 0, 0, 0, 0, 0, 0, 0, 0, 0, 0], [0, 0, 1, 1, 0, 0, 0, 0, 0, 1, 0, 0, 1, 1, 0, 0, 0, 0, 0, 0, 0, 0], [0, 0, 0, 1, 0, 0, 1, 1, 1, 0, 0, 1, 0, 1, 1, 1, 1, 0, 0, 0, 0, 0], [0, 0, 0, 0, 1, 1, 1, 0, 0, 1, 1, 0, 1, 0, 0, 0, 0, 1, 0, 0, 0, 0], [0, 0, 0, 0, 0, 1, 1, 1, 1, 1, 1, 0, 0, 1, 0, 1, 1, 0, 1, 0, 0, 0], [0, 0, 0, 0, 0, 0, 0, 0, 1, 1, 1, 0, 0, 0, 1, 0, 1, 1, 1, 0, 0, 0], [0, 0, 0, 0, 0, 0, 0, 0, 0, 0, 0, 1, 1, 0, 0, 1, 1, 1, 0, 1, 0, 0], [0, 0, 0, 0, 0, 0, 0, 0, 0, 0, 0, 0, 0, 1, 1, 0, 1, 0, 0, 1, 0, 1], [0, 0, 0, 0, 0, 0, 0, 0, 0, 0, 0, 0, 0, 0, 0, 1, 0, 1, 1, 1, 1, 0]], "G_Z": [[1, 1, 1, 0, 0, 1, 0, 1, 1, 1, 0, 0, 0, 0, 0, 0, 0, 0, 0, 0, 0, 0], [0, 0, 1, 1, 0, 1, 0, 1, 0, 1, 0, 1, 1, 0, 0, 1, 0, 1, 0, 0, 0, 0], [0, 1, 1, 0, 0, 0, 1, 1, 0, 0, 1, 1, 1, 0, 0, 1, 0, 1, 0, 0, 0, 0], [0, 0, 0, 1, 1, 1, 1, 0, 1, 1, 1, 0, 0, 0, 0, 1, 0, 1, 0, 0, 0, 0], [0, 0, 0, 0, 1, 1, 0, 1, 1, 1, 1, 0, 0, 1, 1, 0, 0, 0, 0, 0, 0, 0], [0, 0, 0, 0, 1, 1, 0, 1, 1, 0, 1, 1, 1, 1, 0, 1, 1, 0, 1, 0, 0, 0], [0, 0, 0, 0, 0, 0, 0, 1, 1, 0, 1, 1, 0, 0, 0, 0, 1, 1, 0, 1, 0, 0], [0, 0, 0, 0, 0, 0, 0, 0, 0, 0, 1, 1, 1, 1, 1, 0, 1, 0, 1, 1, 0, 0], [0, 0, 0, 0, 0, 0, 0, 0, 0, 0, 0, 0, 1, 1, 1, 1, 1, 1, 1, 0, 1, 1], [0, 0, 0, 0, 0, 0, 0, 0, 0, 0, 0, 0, 0, 0, 1, 1, 0, 0, 1, 1, 1, 0]], "gates": [".h(2)", ".h(4)", ".h(6)", ".h(8)", ".h(10)", ".h(12)", ".h(14)", ".h(16)", ".h(18)", ".h(20)", ".cx(2,3)", ".cx(4,5)", ".cx(6,7)", ".cx(8,9)", ".cx(10,11)", ".cx(12,13)", ".cx(14,15)", ".cx(16,17)", ".cx(18,19)", ".cx(20,21)", ".cx(1, 2)", ".cx(3, 4)", ".cx(13, 14)", ".cx(11, 12)", ".cx(9, 10)", ".cx(15, 16)", ".cx(17, 18)", ".cx(19, 20)", ".cx(6, 5)", ".cx(4, 3)", ".cx(2, 1)", ".cx(2, 3)", ".cx(1, 0)", ".cx(8, 7)", ".cx(0, 1)", ".cx(2, 1)", ".cx(7, 8)", ".cx(5, 6)", ".cx(7, 6)", ".cx(4, 5)", ".cx(5, 4)", ".cx(5, 6)", ".cx(8, 9)", ".cx(10, 9)", ".cx(10, 11)", ".cx(12, 11)", ".cx(12, 13)", ".cx(14, 13)", ".cx(6, 7)", ".cx(6, 5)", ".cx(3, 4)", ".cx(3, 2)", ".cx(14, 15)", ".cx(16, 15)", ".cx(20, 19)", ".cx(18, 19)", ".cx(18, 17)", ".cx(9, 8)", ".cx(8, 7)", ".cx(7, 8)", ".cx(17, 16)", ".cx(16, 17)", ".cx(17, 18)", ".cx(9, 8)", ".cx(10, 9)", ".cx(9, 10)", ".cx(8, 9)", ".cx(11, 10)", ".cx(5, 6)", ".cx(4, 5)", ".cx(5, 6)", ".cx(4, 3)", ".cx(15, 16)", ".cx(16, 17)", ".cx(15, 14)", ".cx(13, 14)", ".cx(13, 12)", ".cx(2, 1)", ".cx(11, 12)", ".cx(10, 9)", ".cx(7, 6)", ".cx(1, 2)", ".cx(5, 4)", ".cx(2, 3)", ".cx(3, 2)", ".cx(3, 4)", ".cx(7, 8)", ".cx(9, 8)", ".cx(10, 11)", ".cx(12, 11)", ".cx(6, 7)", ".cx(8, 7)", ".cx(9, 10)", ".cx(5, 6)", ".cx(14, 13)", ".cx(14, 15)", ".cx(16, 15)", ".cx(13, 12)", ".cx(12, 13)", ".cx(11, 12)", ".cx(1, 2)", ".cx(6, 5)", ".cx(6, 7)", ".cx(11, 10)", ".cx(4, 3)", ".cx(18, 17)", ".cx(17, 18)", ".cx(19, 18)", ".cx(15, 14)", ".cx(14, 13)", ".cx(15, 14)", ".cx(18, 17)", ".cx(13, 14)", ".cx(17, 16)", ".cx(5, 4)", ".cx(18, 17)", ".cx(4, 5)", ".cx(7, 6)", ".cx(10, 9)", ".cx(8, 9)", ".cx(7, 8)", ".cx(16, 17)", ".cx(15, 16)", ".cx(12, 11)", ".cx(10, 11)", ".cx(16, 15)", ".cx(6, 5)", ".cx(14, 15)", ".cx(12, 13)", ".cx(9, 8)", ".cx(21, 20)", ".cx(17, 16)", ".cx(16, 17)", ".cx(15, 16)", ".cx(17, 16)", ".cx(20, 21)", ".cx(21, 20)", ".cx(20, 21)", ".cx(20, 21)", ".cx(20, 21)", ".cx(20, 21)", ".cx(20, 21)", ".cx(20, 21)", ".cx(20, 21)", ".cx(20, 21)", ".cx(20, 21)", ".cx(20, 21)", ".cx(20, 21)", ".cx(20, 21)", ".cx(20, 21)"]}, {"n": 22, "k": 2, "d": 4, "G_X": [[0, 1, 1, 0, 0, 0, 1, 1, 0, 1, 0, 1, 1, 1, 0, 0, 0, 0, 0, 0, 0, 0], [1, 1, 1, 0, 1, 1, 1, 0, 0, 1, 1, 0, 1, 1, 0, 0, 0, 0, 0, 0, 0, 0], [0, 0, 1, 1, 0, 0, 1, 0, 1, 0, 1, 1, 1, 1, 0, 0, 0, 0, 0, 0, 0, 0], [0, 0, 0, 1, 1, 1, 1, 0, 1, 0, 0, 1, 1, 0, 1, 0, 0, 0, 0, 0, 0, 0], [0, 0, 0, 0, 0, 1, 1, 1, 0, 0, 1, 0, 0, 1, 1, 0, 1, 1, 1, 0, 0, 0], [0, 0, 0, 0, 0, 0, 0, 1, 1, 0, 1, 0, 1, 0, 0, 1, 1, 0, 0, 0, 0, 0], [0, 0, 0, 0, 0, 0, 0, 0, 1, 1, 1, 0, 0, 1, 1, 0, 1, 1, 0, 1, 0, 0], [0, 0, 0, 0, 0, 0, 0, 0, 0, 1, 1, 1, 0, 1, 1, 0, 1, 1, 1, 0, 1, 1], [0, 0, 0, 0, 0, 0, 0, 0, 0, 0, 0, 0, 0, 0, 0, 1, 1, 1, 0, 0, 1, 1], [0, 0, 0, 0, 0, 0, 0, 0, 0, 0, 0, 0, 0, 0, 1, 1, 0, 0, 1, 1, 1, 0]], "G_Z": [[1, 0, 0, 1, 1, 0, 0, 1, 0, 1, 1, 0, 0, 0, 0, 0, 0, 0, 0, 0, 0, 0], [0, 1, 0, 1, 1, 0, 1, 0, 0, 1, 1, 0, 1, 0, 0, 0, 0, 0, 0, 0, 0, 0], [0, 1, 1, 0, 1, 1, 0, 0, 0, 1, 0, 0, 0, 1, 0, 0, 0, 0, 0, 0, 0, 0], [0, 0, 0, 1, 0, 0, 1, 1, 1, 1, 0, 1, 0, 0, 0, 0, 0, 0, 0, 0, 0, 0], [0, 0, 0, 0, 1, 1, 1, 1, 1, 0, 0, 1, 0, 1, 1, 1, 1, 0, 0, 0, 0, 0], [0, 0, 0, 0, 0, 0, 1, 1, 1, 0, 0, 1, 0, 1, 1, 1, 1, 1, 0, 1, 1, 0], [0, 0, 0, 0, 0, 0, 0, 0, 1, 0, 1, 1, 1, 0, 1, 1, 0, 0, 0, 1, 1, 0], [0, 0, 0, 0, 0, 0, 0, 0, 1, 1, 0, 0, 0, 1, 1, 0, 1, 0, 1, 1, 1, 0], [0, 0, 0, 0, 0, 0, 0, 0, 0, 0, 0, 0, 1, 1, 1, 1, 0, 1, 1, 1, 0, 0], [0, 0, 0, 0, 0, 0, 0, 0, 0, 0, 0, 0, 0, 0, 0, 1, 1, 0, 1, 1, 1, 1]], "gates": [".h(2)", ".h(4)", ".h(6)", ".h(8)", ".h(10)", ".h(12)", ".h(14)", ".h(16)", ".h(18)", ".h(20)", ".cx(2,3)", ".cx(4,5)", ".cx(6,7)", ".cx(8,9)", ".cx(10,11)", ".cx(12,13)", ".cx(14,15)", ".cx(16,17)", ".cx(18,19)", ".cx(20,21)", ".cx(1, 2)", ".cx(3, 4)", ".cx(5, 6)", ".cx(13, 14)", ".cx(11, 12)", ".cx(9, 10)", ".cx(15, 16)", ".cx(17, 18)", ".cx(0, 1)", ".cx(8, 7)", ".cx(7, 8)", ".cx(20, 19)", ".cx(19, 20)", ".cx(2, 1)", ".cx(4, 3)", ".cx(3, 2)", ".cx(2, 3)", ".cx(4, 5)", ".cx(6, 5)", ".cx(6, 7)", ".cx(8, 9)", ".cx(7, 8)", ".cx(10, 9)", ".cx(1, 2)", ".cx(1, 0)", ".cx(3, 4)", ".cx(2, 3)", ".cx(5, 4)", ".cx(7, 6)", ".cx(5, 6)", ".cx(10, 11)", ".cx(12, 11)", ".cx(12, 13)", ".cx(14, 13)", ".cx(14, 15)", ".cx(16, 15)", ".cx(16, 17)", ".cx(18, 17)", ".cx(18, 19)", ".cx(19, 20)", ".cx(19, 18)", ".cx(2, 1)", ".cx(4, 3)", ".cx(1, 2)", ".cx(1, 0)", ".cx(17, 16)", ".cx(15, 16)", ".cx(15, 14)", ".cx(13, 14)", ".cx(13, 12)", ".cx(11, 10)", ".cx(11, 12)", ".cx(9, 8)", ".cx(10, 9)", ".cx(9, 10)", ".cx(18, 17)", ".cx(17, 18)", ".cx(10, 11)", ".cx(3, 4)", ".cx(4, 5)", ".cx(3, 4)", ".cx(11, 10)", ".cx(8, 7)", ".cx(6, 7)", ".cx(6, 5)", ".cx(12, 11)", ".cx(9, 8)", ".cx(8, 9)", ".cx(7, 8)", ".cx(9, 10)", ".cx(5, 4)", ".cx(5, 6)", ".cx(8, 9)", ".cx(7, 6)", ".cx(12, 13)", ".cx(11, 10)", ".cx(10, 9)", ".cx(14, 13)", ".cx(14, 15)", ".cx(16, 15)", ".cx(17, 16)", ".cx(3, 2)", ".cx(10, 11)", ".cx(15, 16)", ".cx(18, 17)", ".cx(19, 18)", ".cx(18, 19)", ".cx(16, 17)", ".cx(17, 18)", ".cx(18, 17)", ".cx(16, 15)", ".cx(15, 16)", ".cx(16, 15)", ".cx(11, 12)", ".cx(13, 12)", ".cx(10, 11)", ".cx(15, 14)", ".cx(12, 11)", ".cx(9, 10)", ".cx(20, 21)", ".cx(20, 19)", ".cx(13, 14)", ".cx(16, 15)", ".cx(11, 10)", ".cx(10, 11)", ".cx(11, 10)", ".cx(12, 11)", ".cx(11, 12)", ".cx(8, 7)", ".cx(6, 7)", ".cx(9, 8)", ".cx(12, 13)", ".cx(8, 9)", ".cx(10, 9)", ".cx(18, 17)", ".cx(6, 5)", ".cx(4, 5)", ".cx(4, 3)", ".cx(11, 12)", ".cx(11, 12)", ".cx(11, 12)", ".cx(11, 12)", ".cx(11, 12)", ".cx(11, 12)", ".cx(11, 12)", ".cx(11, 12)", ".cx(11, 12)", ".cx(11, 12)", ".cx(11, 12)", ".cx(11, 12)"]}, {"n": 22, "k": 2, "d": 4, "G_X": [[1, 1, 1, 0, 0, 1, 0, 1, 0, 1, 1, 0, 0, 0, 0, 0, 0, 0, 0, 0, 0, 0], [0, 1, 0, 1, 0, 0, 1, 0, 1, 0, 1, 0, 0, 0, 0, 0, 0, 0, 0, 0, 0, 0], [0, 0, 1, 1, 0, 1, 1, 0, 1, 0, 1, 0, 0, 0, 0, 1, 1, 1, 0, 0, 0, 0], [0, 0, 1, 0, 1, 1, 0, 0, 1, 1, 1, 1, 1, 1, 0, 1, 1, 1, 0, 0, 0, 0], [0, 0, 0, 0, 0, 1, 0, 0, 1, 1, 0, 0, 1, 0, 0, 0, 1, 1, 0, 0, 0, 0], [0, 0, 0, 0, 0, 0, 0, 0, 0, 1, 0, 1, 0, 1, 0, 0, 1, 0, 0, 1, 0, 0], [0, 0, 0, 0, 0, 0, 1, 1, 1, 0, 0, 0, 0, 1, 1, 0, 1, 1, 0, 1, 0, 0], [0, 0, 0, 0, 0, 0, 0, 0, 0, 0, 1, 1, 1, 0, 0, 0, 1, 1, 1, 1, 0, 0], [0, 0, 0, 0, 0, 0, 0, 0, 0, 0, 0, 0, 1, 1, 1, 1, 1, 1, 1, 0, 0, 1], [0, 0, 0, 0, 0, 0, 0, 0, 0, 0, 0, 0, 0, 0, 1, 0, 1, 0, 1, 0, 1, 0]], "G_Z": [[1, 0, 1, 0, 1, 1, 1, 1, 0, 1, 1, 1, 0, 0, 0, 0, 0, 0, 0, 0, 0, 0], [0, 0, 1, 1, 1, 1, 0, 0, 0, 1, 1, 1, 0, 0, 0, 0, 0, 0, 0, 0, 0, 0], [0, 1, 0, 1, 0, 0, 1, 0, 0, 0, 1, 1, 0, 1, 0, 1, 0, 0, 0, 0, 0, 0], [0, 1, 0, 1, 0, 1, 0, 0, 1, 1, 1, 0, 1, 1, 0, 0, 0, 0, 0, 0, 0, 0], [0, 0, 0, 0, 1, 0, 1, 1, 0, 0, 1, 1, 1, 0, 1, 1, 1, 0, 0, 0, 0, 0], [0, 0, 0, 0, 0, 0, 0, 1, 1, 0, 1, 1, 1, 0, 0, 0, 1, 1, 1, 0, 0, 0], [0, 0, 0, 0, 0, 0, 0, 0, 1, 1, 1, 0, 1, 0, 0, 1, 1, 0, 1, 0, 0, 0], [0, 0, 0, 0, 0, 0, 0, 0, 0, 0, 0, 1, 1, 0, 0, 1, 0, 1, 0, 1, 0, 1], [0, 0, 0, 0, 0, 0, 0, 0, 0, 0, 0, 0, 1, 1, 1, 1, 0, 1, 1, 1, 0, 0], [0, 0, 0, 0, 0, 0, 0, 0, 0, 0, 0, 0, 0, 0, 1, 0, 1, 1, 1, 1, 1, 0]], "gates": [".h(2)", ".h(4)", ".h(6)", ".h(8)", ".h(10)", ".h(12)", ".h(14)", ".h(16)", ".h(18)", ".h(20)", ".cx(2,3)", ".cx(4,5)", ".cx(6,7)", ".cx(8,9)", ".cx(10,11)", ".cx(12,13)", ".cx(14,15)", ".cx(16,17)", ".cx(18,19)", ".cx(20,21)", ".cx(2, 1)", ".cx(4, 3)", ".cx(11, 12)", ".cx(13, 14)", ".cx(9, 10)", ".cx(15, 16)", ".cx(7, 8)", ".cx(1, 0)", ".cx(20, 19)", ".cx(5, 6)", ".cx(1, 2)", ".cx(3, 4)", ".cx(3, 2)", ".cx(18, 17)", ".cx(17, 18)", ".cx(19, 20)", ".cx(19, 18)", ".cx(6, 5)", ".cx(6, 7)", ".cx(8, 7)", ".cx(5, 4)", ".cx(4, 5)", ".cx(6, 5)", ".cx(8, 9)", ".cx(10, 9)", ".cx(0, 1)", ".cx(2, 1)", ".cx(2, 3)", ".cx(4, 3)", ".cx(5, 6)", ".cx(7, 6)", ".cx(12, 11)", ".cx(12, 13)", ".cx(14, 13)", ".cx(11, 10)", ".cx(10, 11)", ".cx(9, 10)", ".cx(9, 8)", ".cx(11, 12)", ".cx(10, 11)", ".cx(13, 12)", ".cx(16, 15)", ".cx(14, 15)", ".cx(17, 16)", ".cx(16, 17)", ".cx(15, 16)", ".cx(15, 14)", ".cx(13, 14)", ".cx(7, 8)", ".cx(12, 11)", ".cx(10, 9)", ".cx(16, 15)", ".cx(16, 17)", ".cx(18, 17)", ".cx(14, 15)", ".cx(6, 5)", ".cx(5, 4)", ".cx(4, 5)", ".cx(3, 4)", ".cx(6, 7)", ".cx(8, 7)", ".cx(4, 3)", ".cx(3, 2)", ".cx(6, 5)", ".cx(5, 6)", ".cx(4, 5)", ".cx(6, 5)", ".cx(4, 3)", ".cx(2, 3)", ".cx(1, 2)", ".cx(2, 3)", ".cx(9, 8)", ".cx(8, 9)", ".cx(7, 8)", ".cx(7, 6)", ".cx(8, 9)", ".cx(17, 18)", ".cx(18, 19)", ".cx(17, 18)", ".cx(11, 12)", ".cx(12, 13)", ".cx(13, 14)", ".cx(14, 13)", ".cx(13, 12)", ".cx(11, 10)", ".cx(6, 5)", ".cx(10, 9)", ".cx(9, 10)", ".cx(9, 8)", ".cx(8, 7)", ".cx(8, 9)", ".cx(12, 11)", ".cx(17, 16)", ".cx(15, 14)", ".cx(5, 6)", ".cx(7, 6)", ".cx(14, 15)", ".cx(14, 13)", ".cx(11, 10)", ".cx(11, 12)", ".cx(16, 17)", ".cx(18, 17)", ".cx(13, 12)", ".cx(12, 13)", ".cx(20, 19)", ".cx(14, 13)", ".cx(15, 16)", ".cx(18, 19)", ".cx(16, 15)", ".cx(8, 7)", ".cx(14, 15)", ".cx(21, 20)", ".cx(20, 21)", ".cx(21, 20)", ".cx(15, 14)", ".cx(16, 17)", ".cx(8, 7)", ".cx(14, 15)", ".cx(12, 11)", ".cx(12, 11)", ".cx(12, 11)", ".cx(12, 11)", ".cx(12, 11)", ".cx(12, 11)", ".cx(12, 11)", ".cx(12, 11)", ".cx(12, 11)", ".cx(12, 11)", ".cx(12, 11)", ".cx(12, 11)"]}, {"n": 22, "k": 2, "d": 4, "G_X": [[1, 1, 0, 0, 0, 0, 1, 1, 0, 1, 1, 0, 0, 0, 0, 0, 0, 0, 0, 0, 0, 0], [0, 1, 0, 1, 0, 0, 1, 1, 0, 1, 1, 1, 1, 1, 1, 0, 0, 0, 0, 0, 0, 0], [0, 0, 1, 1, 0, 1, 0, 0, 1, 1, 0, 1, 1, 1, 1, 0, 0, 0, 0, 0, 0, 0], [0, 0, 0, 1, 0, 1, 1, 1, 1, 1, 0, 0, 0, 1, 1, 1, 1, 0, 0, 0, 0, 0], [0, 0, 0, 0, 1, 1, 0, 0, 1, 0, 1, 0, 0, 1, 1, 0, 0, 1, 1, 0, 0, 0], [0, 0, 0, 0, 0, 0, 0, 0, 1, 1, 1, 1, 1, 1, 0, 1, 0, 0, 1, 0, 0, 0], [0, 0, 0, 0, 0, 0, 1, 0, 1, 0, 0, 0, 1, 1, 0, 0, 0, 1, 1, 0, 0, 0], [0, 0, 0, 0, 0, 0, 0, 0, 0, 0, 1, 0, 1, 0, 1, 0, 0, 0, 1, 1, 0, 0], [0, 0, 0, 0, 0, 0, 0, 0, 0, 0, 0, 0, 1, 1, 0, 1, 1, 1, 0, 0, 1, 0], [0, 0, 0, 0, 0, 0, 0, 0, 0, 0, 0, 0, 0, 0, 0, 0, 1, 1, 1, 1, 0, 1]], "G_Z": [[1, 1, 1, 1, 1, 0, 1, 0, 1, 1, 0, 0, 0, 0, 0, 0, 0, 0, 0, 0, 0, 0], [0, 1, 0, 1, 0, 0, 0, 0, 0, 0, 1, 1, 1, 1, 0, 0, 0, 0, 0, 0, 0, 0], [0, 0, 1, 1, 1, 0, 1, 1, 1, 0, 0, 1, 0, 0, 0, 0, 0, 0, 0, 0, 0, 0], [0, 0, 1, 1, 0, 0, 0, 1, 1, 0, 1, 0, 1, 0, 0, 1, 0, 0, 0, 0, 0, 0], [0, 0, 0, 0, 0, 1, 0, 0, 0, 1, 1, 0, 1, 0, 1, 0, 1, 0, 1, 0, 0, 0], [0, 0, 0, 0, 0, 0, 1, 1, 1, 1, 1, 1, 0, 1, 0, 0, 1, 0, 1, 0, 0, 0], [0, 0, 0, 0, 0, 0, 0, 0, 1, 1, 1, 1, 0, 0, 1, 0, 1, 1, 0, 0, 0, 0], [0, 0, 0, 0, 0, 0, 0, 0, 1, 1, 1, 1, 1, 0, 0, 0, 0, 1, 1, 1, 0, 1], [0, 0, 0, 0, 0, 0, 0, 0, 0, 0, 0, 1, 1, 1, 1, 0, 0, 1, 1, 1, 1, 1], [0, 0, 0, 0, 0, 0, 0, 0, 0, 0, 0, 0, 0, 0, 0, 1, 1, 1, 1, 1, 1, 0]], "gates": [".h(2)", ".h(4)", ".h(6)", ".h(8)", ".h(10)", ".h(12)", ".h(14)", ".h(16)", ".h(18)", ".h(20)", ".cx(2,3)", ".cx(4,5)", ".cx(6,7)", ".cx(8,9)", ".cx(10,11)", ".cx(12,13)", ".cx(14,15)", ".cx(16,17)", ".cx(18,19)", ".cx(20,21)", ".cx(2, 1)", ".cx(4, 3)", ".cx(6, 5)", ".cx(8, 7)", ".cx(10, 9)", ".cx(12, 11)", ".cx(14, 13)", ".cx(16, 15)", ".cx(18, 17)", ".cx(1, 0)", ".cx(20, 19)", ".cx(1, 2)", ".cx(3, 4)", ".cx(2, 3)", ".cx(3, 2)", ".cx(2, 1)", ".cx(0, 1)", ".cx(5, 6)", ".cx(5, 4)", ".cx(4, 3)", ".cx(3, 2)", ".cx(4, 5)", ".cx(7, 6)", ".cx(7, 8)", ".cx(9, 8)", ".cx(9, 10)", ".cx(11, 10)", ".cx(11, 12)", ".cx(13, 12)", ".cx(13, 14)", ".cx(15, 14)", ".cx(15, 16)", ".cx(17, 16)", ".cx(17, 18)", ".cx(19, 18)", ".cx(19, 20)", ".cx(6, 7)", ".cx(5, 6)", ".cx(6, 5)", ".cx(4, 5)", ".cx(5, 4)", ".cx(4, 3)", ".cx(3, 4)", ".cx(8, 9)", ".cx(10, 9)", ".cx(7, 8)", ".cx(8, 7)", ".cx(10, 11)", ".cx(12, 11)", ".cx(12, 13)", ".cx(5, 4)", ".cx(9, 10)", ".cx(8, 9)", ".cx(9, 10)", ".cx(1, 2)", ".cx(9, 8)", ".cx(11, 10)", ".cx(6, 7)", ".cx(6, 5)", ".cx(14, 15)", ".cx(13, 14)", ".cx(16, 17)", ".cx(18, 17)", ".cx(15, 16)", ".cx(14, 15)", ".cx(14, 13)", ".cx(18, 19)", ".cx(20, 19)", ".cx(21, 20)", ".cx(16, 15)", ".cx(16, 17)", ".cx(20, 19)", ".cx(11, 12)", ".cx(12, 13)", ".cx(11, 12)", ".cx(13, 12)", ".cx(4, 5)", ".cx(7, 6)", ".cx(7, 8)", ".cx(15, 14)", ".cx(15, 16)", ".cx(5, 4)", ".cx(3, 4)", ".cx(2, 3)", ".cx(10, 11)", ".cx(10, 9)", ".cx(8, 9)", ".cx(8, 7)", ".cx(17, 18)", ".cx(13, 14)", ".cx(16, 15)", ".cx(16, 17)", ".cx(14, 13)", ".cx(12, 13)", ".cx(12, 11)", ".cx(11, 12)", ".cx(15, 14)", ".cx(5, 6)", ".cx(6, 5)", ".cx(5, 6)", ".cx(5, 4)", ".cx(6, 7)", ".cx(17, 16)", ".cx(14, 15)", ".cx(18, 17)", ".cx(11, 10)", ".cx(12, 13)", ".cx(13, 12)", ".cx(11, 12)", ".cx(17, 18)", ".cx(21, 20)", ".cx(9, 10)", ".cx(9, 8)", ".cx(8, 9)", ".cx(8, 7)", ".cx(6, 7)", ".cx(7, 6)", ".cx(6, 7)", ".cx(15, 16)", ".cx(15, 14)", ".cx(13, 14)", ".cx(13, 12)", ".cx(12, 11)", ".cx(13, 12)", ".cx(12, 11)", ".cx(12, 11)", ".cx(12, 11)", ".cx(12, 11)", ".cx(12, 11)", ".cx(12, 11)"]}, {"n": 22, "k": 2, "d": 4, "G_X": [[1, 0, 0, 0, 1, 0, 1, 1, 1, 0, 0, 0, 0, 0, 0, 0, 0, 0, 0, 0, 0, 0], [1, 1, 1, 0, 1, 1, 0, 1, 0, 1, 1, 0, 0, 0, 1, 0, 0, 0, 0, 0, 0, 0], [1, 1, 0, 1, 1, 1, 1, 0, 0, 1, 1, 1, 1, 0, 0, 0, 0, 0, 0, 0, 0, 0], [0, 0, 1, 0, 1, 1, 1, 0, 0, 1, 0, 0, 1, 0, 1, 0, 0, 0, 0, 0, 0, 0], [0, 0, 0, 0, 0, 1, 1, 0, 0, 1, 0, 0, 1, 0, 1, 1, 1, 0, 1, 0, 0, 0], [0, 0, 0, 0, 0, 0, 0, 0, 1, 1, 0, 1, 0, 0, 1, 1, 0, 1, 1, 0, 0, 0], [0, 0, 0, 0, 0, 0, 0, 1, 1, 0, 1, 0, 1, 0, 0, 1, 1, 1, 1, 1, 0, 0], [0, 0, 0, 0, 0, 0, 0, 0, 0, 0, 1, 1, 1, 1, 0, 0, 0, 1, 1, 1, 0, 0], [0, 0, 0, 0, 0, 0, 0, 0, 0, 0, 0, 0, 1, 0, 1, 1, 0, 0, 0, 1, 1, 0], [0, 0, 0, 0, 0, 0, 0, 0, 0, 0, 0, 0, 0, 0, 0, 0, 1, 1, 0, 1, 1, 1]], "G_Z": [[1, 1, 1, 1, 1, 1, 1, 0, 1, 0, 1, 1, 0, 0, 0, 0, 0, 0, 0, 0, 0, 0], [0, 1, 0, 1, 0, 0, 1, 1, 0, 1, 1, 1, 0, 0, 0, 0, 0, 0, 0, 0, 0, 0], [0, 0, 1, 0, 1, 0, 1, 1, 1, 1, 1, 1, 1, 1, 1, 0, 0, 0, 0, 0, 0, 0], [0, 0, 1, 1, 0, 1, 0, 1, 1, 1, 1, 0, 0, 1, 1, 1, 0, 0, 0, 0, 0, 0], [0, 0, 0, 0, 0, 0, 0, 1, 1, 1, 1, 0, 0, 1, 1, 0, 1, 0, 1, 1, 0, 0], [0, 0, 0, 0, 0, 0, 1, 1, 0, 0, 1, 1, 1, 1, 0, 0, 1, 0, 1, 1, 0, 0], [0, 0, 0, 0, 0, 0, 0, 0, 0, 0, 1, 0, 1, 1, 1, 1, 0, 1, 1, 1, 0, 0], [0, 0, 0, 0, 0, 0, 0, 0, 0, 1, 1, 1, 1, 0, 0, 1, 0, 0, 1, 0, 0, 0], [0, 0, 0, 0, 0, 0, 0, 0, 0, 1, 1, 1, 1, 1, 0, 1, 1, 1, 0, 1, 1, 0], [0, 0, 0, 0, 0, 0, 0, 0, 0, 0, 0, 0, 0, 0, 0, 1, 1, 1, 0, 1, 0, 1]], "gates": [".h(2)", ".h(4)", ".h(6)", ".h(8)", ".h(10)", ".h(12)", ".h(14)", ".h(16)", ".h(18)", ".h(20)", ".cx(2,3)", ".cx(4,5)", ".cx(6,7)", ".cx(8,9)", ".cx(10,11)", ".cx(12,13)", ".cx(14,15)", ".cx(16,17)", ".cx(18,19)", ".cx(20,21)", ".cx(1, 2)", ".cx(3, 4)", ".cx(17, 18)", ".cx(15, 16)", ".cx(13, 14)", ".cx(19, 20)", ".cx(10, 9)", ".cx(8, 7)", ".cx(6, 5)", ".cx(4, 3)", ".cx(2, 1)", ".cx(2, 3)", ".cx(1, 0)", ".cx(12, 11)", ".cx(0, 1)", ".cx(2, 1)", ".cx(5, 4)", ".cx(5, 6)", ".cx(7, 6)", ".cx(7, 8)", ".cx(11, 12)", ".cx(9, 10)", ".cx(11, 10)", ".cx(4, 5)", ".cx(4, 3)", ".cx(9, 8)", ".cx(20, 19)", ".cx(18, 19)", ".cx(18, 17)", ".cx(16, 15)", ".cx(16, 17)", ".cx(14, 13)", ".cx(13, 12)", ".cx(15, 14)", ".cx(14, 13)", ".cx(3, 2)", ".cx(3, 4)", ".cx(6, 5)", ".cx(6, 7)", ".cx(8, 9)", ".cx(8, 7)", ".cx(10, 11)", ".cx(10, 9)", ".cx(12, 13)", ".cx(12, 11)", ".cx(2, 1)", ".cx(4, 3)", ".cx(5, 4)", ".cx(4, 3)", ".cx(5, 6)", ".cx(1, 2)", ".cx(3, 2)", ".cx(2, 3)", ".cx(1, 0)", ".cx(14, 15)", ".cx(17, 16)", ".cx(15, 16)", ".cx(16, 15)", ".cx(17, 18)", ".cx(14, 15)", ".cx(15, 14)", ".cx(13, 14)", ".cx(13, 12)", ".cx(11, 12)", ".cx(7, 8)", ".cx(7, 6)", ".cx(4, 5)", ".cx(3, 4)", ".cx(6, 5)", ".cx(6, 7)", ".cx(11, 10)", ".cx(9, 10)", ".cx(8, 9)", ".cx(9, 8)", ".cx(9, 10)", ".cx(4, 5)", ".cx(4, 3)", ".cx(18, 19)", ".cx(19, 18)", ".cx(18, 17)", ".cx(14, 15)", ".cx(16, 15)", ".cx(14, 13)", ".cx(12, 13)", ".cx(10, 11)", ".cx(11, 12)", ".cx(12, 11)", ".cx(12, 13)", ".cx(9, 10)", ".cx(10, 11)", ".cx(8, 7)", ".cx(17, 16)", ".cx(16, 17)", ".cx(15, 16)", ".cx(18, 17)", ".cx(17, 18)", ".cx(19, 18)", ".cx(15, 14)", ".cx(13, 12)", ".cx(13, 14)", ".cx(10, 9)", ".cx(9, 8)", ".cx(7, 8)", ".cx(10, 9)", ".cx(6, 7)", ".cx(16, 17)", ".cx(17, 18)", ".cx(18, 17)", ".cx(16, 17)", ".cx(2, 3)", ".cx(8, 7)", ".cx(4, 5)", ".cx(14, 13)", ".cx(9, 10)", ".cx(11, 10)", ".cx(11, 12)", ".cx(13, 12)", ".cx(13, 14)", ".cx(18, 17)", ".cx(17, 18)", ".cx(18, 17)", ".cx(18, 17)", ".cx(18, 17)", ".cx(18, 17)", ".cx(18, 17)", ".cx(18, 17)", ".cx(18, 17)", ".cx(18, 17)", ".cx(18, 17)", ".cx(18, 17)"]}, {"n": 22, "k": 2, "d": 5, "G_X": [[1, 1, 1, 1, 0, 0, 1, 1, 0, 1, 1, 0, 0, 0, 0, 0, 0, 0, 0, 0, 0, 0], [0, 1, 0, 0, 1, 0, 0, 1, 0, 1, 0, 1, 1, 0, 0, 0, 0, 0, 0, 0, 0, 0], [0, 0, 1, 1, 0, 0, 0, 0, 0, 0, 1, 1, 1, 1, 0, 1, 0, 0, 0, 0, 0, 0], [0, 0, 0, 0, 0, 1, 0, 1, 0, 0, 1, 1, 0, 1, 0, 1, 1, 0, 0, 0, 0, 0], [0, 0, 0, 1, 1, 1, 1, 0, 1, 1, 0, 1, 1, 1, 1, 0, 0, 0, 0, 0, 0, 0], [0, 0, 0, 0, 0, 1, 1, 1, 1, 1, 0, 1, 1, 1, 0, 0, 0, 1, 0, 0, 0, 0], [0, 0, 0, 0, 0, 0, 0, 0, 0, 0, 0, 1, 1, 1, 0, 1, 1, 1, 0, 1, 0, 0], [0, 0, 0, 0, 0, 0, 0, 1, 1, 0, 0, 0, 0, 0, 1, 0, 0, 1, 1, 1, 0, 0], [0, 0, 0, 0, 0, 0, 0, 0, 0, 0, 0, 0, 1, 1, 1, 1, 0, 1, 1, 1, 1, 0], [0, 0, 0, 0, 0, 0, 0, 0, 0, 0, 0, 0, 0, 0, 0, 1, 1, 0, 1, 1, 1, 1]], "G_Z": [[1, 1, 0, 0, 0, 0, 1, 0, 0, 1, 0, 0, 0, 0, 0, 0, 0, 0, 0, 0, 0, 0], [0, 0, 1, 0, 1, 1, 0, 1, 1, 1, 1, 0, 1, 1, 0, 0, 0, 0, 0, 0, 0, 0], [0, 1, 1, 1, 1, 1, 0, 0, 0, 1, 0, 0, 1, 1, 0, 0, 0, 0, 0, 0, 0, 0], [0, 0, 0, 1, 1, 1, 0, 0, 0, 1, 0, 1, 1, 0, 0, 1, 1, 0, 0, 0, 0, 0], [0, 0, 0, 0, 0, 1, 1, 0, 0, 0, 1, 1, 1, 1, 1, 0, 0, 1, 0, 0, 0, 0], [0, 0, 0, 0, 0, 0, 1, 1, 0, 0, 0, 1, 0, 0, 0, 1, 1, 1, 0, 0, 0, 0], [0, 0, 0, 0, 0, 0, 0, 0, 1, 0, 0, 1, 1, 0, 1, 0, 1, 1, 1, 0, 0, 0], [0, 0, 0, 0, 0, 0, 0, 0, 1, 1, 1, 0, 1, 0, 1, 0, 1, 1, 0, 1, 0, 0], [0, 0, 0, 0, 0, 0, 0, 0, 0, 0, 0, 1, 1, 0, 0, 0, 1, 0, 1, 1, 1, 0], [0, 0, 0, 0, 0, 0, 0, 0, 0, 0, 0, 0, 0, 1, 1, 1, 0, 1, 1, 1, 0, 1]], "gates": [".h(2)", ".h(4)", ".h(6)", ".h(8)", ".h(10)", ".h(12)", ".h(14)", ".h(16)", ".h(18)", ".h(20)", ".cx(2,3)", ".cx(4,5)", ".cx(6,7)", ".cx(8,9)", ".cx(10,11)", ".cx(12,13)", ".cx(14,15)", ".cx(16,17)", ".cx(18,19)", ".cx(20,21)", ".cx(1, 2)", ".cx(3, 4)", ".cx(17, 18)", ".cx(19, 20)", ".cx(15, 16)", ".cx(13, 14)", ".cx(11, 12)", ".cx(9, 10)", ".cx(6, 5)", ".cx(8, 7)", ".cx(4, 3)", ".cx(2, 1)", ".cx(1, 0)", ".cx(3, 2)", ".cx(2, 1)", ".cx(0, 1)", ".cx(2, 3)", ".cx(7, 8)", ".cx(5, 6)", ".cx(4, 5)", ".cx(6, 7)", ".cx(5, 6)", ".cx(8, 9)", ".cx(7, 8)", ".cx(5, 4)", ".cx(10, 9)", ".cx(10, 11)", ".cx(12, 11)", ".cx(12, 13)", ".cx(14, 13)", ".cx(14, 15)", ".cx(16, 15)", ".cx(16, 17)", ".cx(18, 17)", ".cx(18, 19)", ".cx(20, 19)", ".cx(3, 4)", ".cx(7, 6)", ".cx(9, 8)", ".cx(9, 10)", ".cx(6, 7)", ".cx(8, 7)", ".cx(4, 3)", ".cx(4, 5)", ".cx(2, 3)", ".cx(3, 2)", ".cx(11, 10)", ".cx(11, 12)", ".cx(1, 2)", ".cx(7, 6)", ".cx(6, 5)", ".cx(7, 6)", ".cx(8, 9)", ".cx(13, 12)", ".cx(15, 14)", ".cx(14, 13)", ".cx(13, 14)", ".cx(13, 12)", ".cx(12, 13)", ".cx(12, 11)", ".cx(15, 16)", ".cx(17, 16)", ".cx(9, 8)", ".cx(10, 9)", ".cx(9, 8)", ".cx(5, 4)", ".cx(4, 3)", ".cx(5, 6)", ".cx(5, 4)", ".cx(10, 11)", ".cx(17, 18)", ".cx(7, 8)", ".cx(18, 19)", ".cx(19, 18)", ".cx(18, 17)", ".cx(8, 7)", ".cx(9, 10)", ".cx(11, 10)", ".cx(11, 12)", ".cx(16, 15)", ".cx(15, 14)", ".cx(16, 15)", ".cx(13, 12)", ".cx(13, 14)", ".cx(14, 15)", ".cx(17, 16)", ".cx(16, 17)", ".cx(15, 16)", ".cx(6, 5)", ".cx(10, 9)", ".cx(2, 3)", ".cx(3, 4)", ".cx(7, 6)", ".cx(8, 9)", ".cx(6, 5)", ".cx(6, 7)", ".cx(9, 8)", ".cx(8, 7)", ".cx(10, 11)", ".cx(9, 10)", ".cx(12, 11)", ".cx(13, 14)", ".cx(14, 13)", ".cx(15, 14)", ".cx(13, 14)", ".cx(12, 13)", ".cx(16, 15)", ".cx(13, 12)", ".cx(13, 14)", ".cx(14, 15)", ".cx(13, 14)", ".cx(11, 12)", ".cx(8, 9)"]}, {"n": 22, "k": 2, "d": 4, "G_X": [[1, 1, 0, 1, 0, 1, 0, 1, 0, 1, 1, 0, 0, 0, 0, 0, 0, 0, 0, 0, 0, 0], [0, 1, 1, 1, 1, 0, 0, 1, 1, 1, 1, 1, 0, 0, 0, 0, 0, 0, 0, 0, 0, 0], [0, 0, 1, 0, 1, 0, 0, 1, 1, 0, 0, 1, 0, 1, 0, 1, 1, 0, 0, 0, 0, 0], [0, 0, 0, 1, 1, 1, 0, 1, 1, 0, 0, 0, 1, 1, 0, 0, 0, 0, 0, 0, 0, 0], [0, 0, 0, 0, 0, 0, 1, 0, 1, 1, 0, 1, 1, 1, 0, 1, 0, 0, 0, 0, 0, 0], [0, 0, 0, 0, 0, 0, 1, 0, 0, 0, 0, 1, 0, 1, 1, 1, 0, 1, 1, 0, 0, 0], [0, 0, 0, 0, 0, 0, 0, 1, 1, 0, 0, 1, 1, 0, 0, 1, 1, 0, 1, 0, 0, 0], [0, 0, 0, 0, 0, 0, 0, 1, 1, 0, 1, 0, 0, 0, 1, 1, 0, 0, 1, 1, 0, 0], [0, 0, 0, 0, 0, 0, 0, 0, 0, 0, 0, 0, 0, 1, 1, 0, 0, 1, 1, 1, 0, 1], [0, 0, 0, 0, 0, 0, 0, 0, 0, 0, 0, 0, 0, 0, 0, 1, 1, 0, 1, 1, 1, 0]], "G_Z": [[1, 1, 0, 0, 0, 0, 0, 1, 1, 1, 0, 0, 0, 0, 0, 0, 0, 0, 0, 0, 0, 0], [0, 1, 1, 0, 0, 0, 0, 0, 1, 0, 1, 0, 1, 0, 0, 0, 0, 0, 0, 0, 0, 0], [0, 0, 1, 1, 1, 1, 1, 1, 0, 0, 1, 1, 0, 0, 0, 0, 0, 0, 0, 0, 0, 0], [0, 0, 0, 0, 1, 1, 0, 0, 1, 0, 1, 1, 0, 1, 1, 1, 1, 0, 0, 0, 0, 0], [0, 0, 0, 0, 0, 1, 1, 0, 0, 1, 0, 1, 1, 0, 1, 0, 1, 0, 1, 0, 0, 0], [0, 0, 0, 0, 0, 0, 1, 1, 0, 1, 0, 0, 1, 0, 1, 1, 0, 0, 1, 0, 0, 0], [0, 0, 0, 0, 0, 0, 0, 0, 1, 1, 1, 1, 1, 0, 0, 0, 0, 0, 1, 1, 0, 0], [0, 0, 0, 0, 0, 0, 0, 0, 0, 1, 1, 0, 1, 1, 1, 1, 0, 1, 0, 1, 0, 0], [0, 0, 0, 0, 0, 0, 0, 0, 0, 1, 1, 0, 0, 0, 0, 1, 1, 1, 0, 0, 0, 1], [0, 0, 0, 0, 0, 0, 0, 0, 0, 0, 0, 0, 0, 0, 1, 0, 0, 1, 0, 1, 1, 1]], "gates": [".h(2)", ".h(4)", ".h(6)", ".h(8)", ".h(10)", ".h(12)", ".h(14)", ".h(16)", ".h(18)", ".h(20)", ".cx(2,3)", ".cx(4,5)", ".cx(6,7)", ".cx(8,9)", ".cx(10,11)", ".cx(12,13)", ".cx(14,15)", ".cx(16,17)", ".cx(18,19)", ".cx(20,21)", ".cx(2, 1)", ".cx(4, 3)", ".cx(6, 5)", ".cx(8, 7)", ".cx(10, 9)", ".cx(12, 11)", ".cx(14, 13)", ".cx(16, 15)", ".cx(18, 17)", ".cx(1, 0)", ".cx(20, 19)", ".cx(1, 2)", ".cx(3, 4)", ".cx(2, 3)", ".cx(3, 2)", ".cx(2, 1)", ".cx(0, 1)", ".cx(5, 6)", ".cx(4, 5)", ".cx(5, 4)", ".cx(3, 4)", ".cx(19, 20)", ".cx(19, 18)", ".cx(17, 18)", ".cx(15, 16)", ".cx(15, 14)", ".cx(13, 14)", ".cx(11, 12)", ".cx(11, 10)", ".cx(9, 10)", ".cx(7, 8)", ".cx(6, 7)", ".cx(8, 9)", ".cx(7, 8)", ".cx(5, 6)", ".cx(7, 6)", ".cx(9, 10)", ".cx(9, 8)", ".cx(12, 13)", ".cx(13, 12)", ".cx(4, 3)", ".cx(3, 2)", ".cx(4, 3)", ".cx(1, 2)", ".cx(14, 13)", ".cx(4, 5)", ".cx(5, 4)", ".cx(6, 5)", ".cx(8, 7)", ".cx(5, 4)", ".cx(4, 3)", ".cx(6, 7)", ".cx(10, 11)", ".cx(11, 12)", ".cx(9, 10)", ".cx(10, 11)", ".cx(16, 17)", ".cx(14, 15)", ".cx(15, 16)", ".cx(17, 16)", ".cx(14, 15)", ".cx(18, 17)", ".cx(13, 14)", ".cx(13, 12)", ".cx(16, 15)", ".cx(10, 9)", ".cx(9, 8)", ".cx(8, 9)", ".cx(5, 6)", ".cx(7, 6)", ".cx(12, 11)", ".cx(9, 10)", ".cx(8, 7)", ".cx(2, 3)", ".cx(12, 13)", ".cx(10, 9)", ".cx(11, 10)", ".cx(10, 9)", ".cx(13, 12)", ".cx(13, 14)", ".cx(15, 14)", ".cx(17, 16)", ".cx(17, 18)", ".cx(18, 19)", ".cx(17, 18)", ".cx(7, 8)", ".cx(7, 6)", ".cx(11, 12)", ".cx(14, 15)", ".cx(16, 15)", ".cx(17, 16)", ".cx(16, 17)", ".cx(13, 14)", ".cx(14, 13)", ".cx(15, 14)", ".cx(15, 16)", ".cx(16, 15)", ".cx(12, 13)", ".cx(12, 11)", ".cx(10, 11)", ".cx(8, 9)", ".cx(9, 8)", ".cx(6, 7)", ".cx(14, 15)", ".cx(15, 14)", ".cx(14, 15)", ".cx(19, 18)", ".cx(18, 19)", ".cx(19, 18)", ".cx(20, 21)", ".cx(21, 20)", ".cx(20, 21)", ".cx(8, 9)", ".cx(8, 7)", ".cx(9, 10)", ".cx(11, 10)", ".cx(18, 17)", ".cx(17, 18)", ".cx(18, 17)", ".cx(18, 17)", ".cx(18, 17)", ".cx(18, 17)", ".cx(18, 17)", ".cx(18, 17)", ".cx(18, 17)", ".cx(18, 17)", ".cx(18, 17)", ".cx(18, 17)", ".cx(18, 17)", ".cx(18, 17)"]}]